dadan/__init__.py
dadan/__main__.py
dadan/analyze.py
dadan/findword.py
dadan/mmseg.py
dadan/perceptron.py
dadan/textrank.py
dadan/utils.py
dadan/cluster/__init__.py
dadan/cluster/base.py
dadan/cluster/dbscan.py
dadan/cluster/kmeans.py
dadan/cluster/text.py
dadan/data/stopwords.txt
dadan/model/kg.model
dadan/model/ner.model
dadan/model/pos.model
dadan/normal/README.md
dadan/segment/README.md
dadan/segment/nroute.py
dadan/segment/dict/dadan.dict
dadan/segment/dict/user.dict
dadan/segment/model/cws.model
dadan/sentiment/README.md
dadan/sentiment/bayes.py
dadan/sentiment/model/sentiment.model
dadan/topic/lda.py
dadan-0.0.1.dist-info/METADATA
dadan-0.0.1.dist-info/WHEEL
dadan-0.0.1.dist-info/top_level.txt
dadan-0.0.1.dist-info/RECORD
