Metadata-Version: 2.1
Name: dadan
Version: 0.0.1
Summary: dadan Natural Language Processing
Home-page: UNKNOWN
Author: dadan
Author-email: dadan@qq.com
License: MIT
Platform: UNKNOWN
